{"nodes": [{"id": "fork_terminal_example", "label": "Example: fork-terminal skill Glyph rewrite", "file_type": "document", "source_file": "research/agent-skill-dsl/examples/fork-terminal.md", "source_location": null, "source_url": null, "captured_at": "2026-04-20", "author": null, "contributor": null}, {"id": "fork_terminal_triggers_block", "label": "fork-terminal: triggers block", "file_type": "document", "source_file": "research/agent-skill-dsl/examples/fork-terminal.md", "source_location": null, "source_url": null, "captured_at": null, "author": null, "contributor": null}, {"id": "fork_terminal_params_block", "label": "fork-terminal: params block (backend/split/etc)", "file_type": "document", "source_file": "research/agent-skill-dsl/examples/fork-terminal.md", "source_location": null, "source_url": null, "captured_at": null, "author": null, "contributor": null}, {"id": "fork_terminal_dispatch_intent", "label": "fork-terminal: dispatch intent table", "file_type": "document", "source_file": "research/agent-skill-dsl/examples/fork-terminal.md", "source_location": null, "source_url": null, "captured_at": null, "author": null, "contributor": null}, {"id": "fork_terminal_cookbook_refs", "label": "fork-terminal: cookbook() external references", "file_type": "document", "source_file": "research/agent-skill-dsl/examples/fork-terminal.md", "source_location": null, "source_url": null, "captured_at": null, "author": null, "contributor": null}, {"id": "fork_terminal_sub_blocks", "label": "fork-terminal: sub-blocks (fork_with_plan, fork_with_summary, launch, send_followup)", "file_type": "document", "source_file": "research/agent-skill-dsl/examples/fork-terminal.md", "source_location": null, "source_url": null, "captured_at": null, "author": null, "contributor": null}, {"id": "fork_terminal_awkward_announce_once", "label": "Awkward: announce_once is stateful cross-invocation", "file_type": "document", "source_file": "research/agent-skill-dsl/examples/fork-terminal.md", "source_location": null, "source_url": null, "captured_at": null, "author": null, "contributor": null}, {"id": "fork_terminal_awkward_verbatim", "label": "Awkward: verbatim-preservation rules are transform properties", "file_type": "document", "source_file": "research/agent-skill-dsl/examples/fork-terminal.md", "source_location": null, "source_url": null, "captured_at": null, "author": null, "contributor": null}, {"id": "fork_terminal_awkward_soft_heuristics", "label": "Awkward: soft heuristics ('prefer when X') have no slot", "file_type": "document", "source_file": "research/agent-skill-dsl/examples/fork-terminal.md", "source_location": null, "source_url": null, "captured_at": null, "author": null, "contributor": null}, {"id": "fork_terminal_oq_on_disk_artifacts", "label": "Open Question: handling on-disk artifact references (inline/lazy/rewrite)", "file_type": "document", "source_file": "research/agent-skill-dsl/examples/fork-terminal.md", "source_location": null, "source_url": null, "captured_at": null, "author": null, "contributor": null}], "edges": [{"source": "fork_terminal_example", "target": "fork_terminal_triggers_block", "relation": "references", "confidence": "EXTRACTED", "confidence_score": 1.0, "source_file": "research/agent-skill-dsl/examples/fork-terminal.md", "source_location": null, "weight": 1.0}, {"source": "fork_terminal_example", "target": "fork_terminal_params_block", "relation": "references", "confidence": "EXTRACTED", "confidence_score": 1.0, "source_file": "research/agent-skill-dsl/examples/fork-terminal.md", "source_location": null, "weight": 1.0}, {"source": "fork_terminal_example", "target": "fork_terminal_dispatch_intent", "relation": "references", "confidence": "EXTRACTED", "confidence_score": 1.0, "source_file": "research/agent-skill-dsl/examples/fork-terminal.md", "source_location": null, "weight": 1.0}, {"source": "fork_terminal_example", "target": "fork_terminal_cookbook_refs", "relation": "references", "confidence": "EXTRACTED", "confidence_score": 1.0, "source_file": "research/agent-skill-dsl/examples/fork-terminal.md", "source_location": null, "weight": 1.0}, {"source": "fork_terminal_example", "target": "fork_terminal_sub_blocks", "relation": "references", "confidence": "EXTRACTED", "confidence_score": 1.0, "source_file": "research/agent-skill-dsl/examples/fork-terminal.md", "source_location": null, "weight": 1.0}, {"source": "fork_terminal_example", "target": "fork_terminal_awkward_announce_once", "relation": "references", "confidence": "EXTRACTED", "confidence_score": 1.0, "source_file": "research/agent-skill-dsl/examples/fork-terminal.md", "source_location": null, "weight": 1.0}, {"source": "fork_terminal_example", "target": "fork_terminal_awkward_verbatim", "relation": "references", "confidence": "EXTRACTED", "confidence_score": 1.0, "source_file": "research/agent-skill-dsl/examples/fork-terminal.md", "source_location": null, "weight": 1.0}, {"source": "fork_terminal_example", "target": "fork_terminal_awkward_soft_heuristics", "relation": "references", "confidence": "EXTRACTED", "confidence_score": 1.0, "source_file": "research/agent-skill-dsl/examples/fork-terminal.md", "source_location": null, "weight": 1.0}, {"source": "fork_terminal_example", "target": "fork_terminal_oq_on_disk_artifacts", "relation": "references", "confidence": "EXTRACTED", "confidence_score": 1.0, "source_file": "research/agent-skill-dsl/examples/fork-terminal.md", "source_location": null, "weight": 1.0}, {"source": "fork_terminal_example", "target": "design_vision_skill", "relation": "cites", "confidence": "EXTRACTED", "confidence_score": 1.0, "source_file": "research/agent-skill-dsl/examples/fork-terminal.md", "source_location": null, "weight": 1.0}, {"source": "fork_terminal_cookbook_refs", "target": "compilation_model_load_lazy", "relation": "implements", "confidence": "INFERRED", "confidence_score": 0.85, "source_file": "research/agent-skill-dsl/examples/fork-terminal.md", "source_location": null, "weight": 0.85}, {"source": "fork_terminal_oq_on_disk_artifacts", "target": "compilation_model_external_artifact_refs", "relation": "semantically_similar_to", "confidence": "INFERRED", "confidence_score": 0.9, "source_file": "research/agent-skill-dsl/examples/fork-terminal.md", "source_location": null, "weight": 0.9}], "hyperedges": []}